{
  "menu": [
    {
      "url": "/",
      "name": "Dashboards",
      "icon": "menu-icon tf-icons bx bx-home-circle",
      "slug": "dashboard-analytics",
      "badge": [
        "danger",
        "Hello!"
      ]
    },
    {
      "name": "Aktiviti 1: Memahami Gerakan AkalBOT",
      "icon": "menu-icon tf-icons bx bx-layout",
      "slug": "layouts",
      "submenu": [
        {
          "url": "layouts/without-menu",
          "name": "Sub menu",
          "slug": "layouts-without-menu"
        },
        {
          "url": "layouts/without-navbar",
          "name": "Sub menu",
          "slug": "layouts-without-navbar"
        },
        {
          "url": "layouts/container",
          "name": "Sub menu",
          "slug": "layouts-container"
        },
        {
          "url": "layouts/fluid",
          "name": "Sub menu",
          "slug": "layouts-fluid"
        },
        {
          "url": "layouts/blank",
          "name": "Sub menu",
          "slug": "layouts-blank",
          "target": "_blank"
        }
      ]
    },
    {
      "name": "Aktiviti 2: Gerakan AkalBOT - Selipar",
      "icon": "menu-icon tf-icons bx bx-copy",
      "slug": "front-pages",
      "submenu": [
        {
          "url": "layouts/blank",
          "name": "Sub menu",
          "slug": "layouts-blank",
          "target": "_blank"
        }
      ]
    },
    {
      "name": "Aktiviti 3: Jom kenal pasti reka bentuk yang menggerakkan AkalBOT!",
      "icon": "menu-icon tf-icons bx bx-cube-alt",
      "slug": "laravel-example",
      "submenu": [
        {
          "url": "Activity_3/FasaPembangunan",
          "name": "3.1 Fasa Pembangunan Aturcara",
          "slug": "Activity_3-FasaPembangunan"
          
        },
        {
          "url": "Activity_3/AnalisisMasalah",
          "name": "3.2  Analisis Masalah",
          "slug": "Activity_3-AnalisisMasalah"
        },
        {
          "url": "Activity_3/RekaBentuk",
          "name": "3.3  Reka Bentuk AkalBot Menggunakan Carta Alir",
          "slug": "Activity_3-RekaBentuk"
        },
        {
          "url": "Activity_3/ImplementasiAlgoritma",
          "name": "3.4  Implementasi Algortima Kepada Aturcara",
          "slug": "Activity_3-ImplementasiAlgoritma"
        }
      ]
    },
    {
      "name": "Aktiviti 4: Jom gerakkan AkalBOT untuk menang!",
      "icon": "menu-icon tf-icons bx bx bx-dock-top",
      "slug": "laravel-example",
      "submenu": [
        {
          "url": "Activity_4/PerjalananBerbeza",
          "name": "4.1  Terokai Perjalanan Berbeza",
          "slug": "Activity_4-PerjalananBerbeza"
        },
        {
          "url": "Activity_4/PerjalananBerhalangan",
          "name": "4.2  Terokai Perjalanan Berhalangan",
          "slug": "Activity_4-PerjalananBerhalangan"
        }
      ]
    },
    {
      "name": "Aktiviti 5: Anda dah tahu bagaimana AkalBOT boleh bergerak?",
      "icon": "menu-icon tf-icons bx bx-collection",
      "slug": "laravel-example",
      "submenu": [
        {
          "url": "Activity_5/Aturcara",
          "name": "5.1  Aturcara",
          "slug": "Activity_5-Aturcara"
        }
      ]
    },
    {
      "name": "Lampiran",
      "icon": "menu-icon tf-icons bx bx-collection",
      "slug": "laravel-example",
      "submenu": [
        {
       
          "url": "Lampiran/Lampiran",
          "name": "Lampiran A,B,C",
          "slug": "Lampiran-Lampiran"
        }
      ]
    },
    {
      "menuHeader": "Account"
    },
    {
      "name": "Profile",
      "icon": "menu-icon tf-icons bx bx bx-dock-top",
      "url": "pages/account-settings-account",
      "slug": "pages-account-settings-account"
    },
    {
      "menuHeader": "Documentation"
    },
    {
      "url": "https://github.com/themeselection/sneat-bootstrap-html-laravel-admin-template-free/issues",
      "icon": "menu-icon tf-icons bx bx-support",
      "name": "About Us",
      "slug": "support",
      "target": "_blank"
    },
    {
      "url": "https://themeselection.com/demo/sneat-bootstrap-html-admin-template/documentation/laravel-introduction.html",
      "icon": "menu-icon tf-icons bx bx-file",
      "name": "Documentation",
      "slug": "documentation",
      "target": "_blank"
    }
  ]
}